main.py
bigdata_mcp_server-0.0.1.dist-info/METADATA
bigdata_mcp_server-0.0.1.dist-info/WHEEL
bigdata_mcp_server-0.0.1.dist-info/entry_points.txt
bigdata_mcp_server-0.0.1.dist-info/top_level.txt
bigdata_mcp_server-0.0.1.dist-info/RECORD
