Metadata-Version: 2.4
Name: bigdata-mcp-server
Version: 0.0.1
Summary: Bigdata of culture and tourism
Requires-Python: >=3.11
Requires-Dist: fastmcp>=2.2.5
Requires-Dist: pycryptodome>=3.22.0
Requires-Dist: requests>=2.32.3
